Metadata-Version: 2.1
Name: openredirectapp
Version: 0.1
Summary: Open Redirect Vulnerability Scanner
Author: gokul
Author-email: <gokul932554@gmail.com>
Classifier: Development Status :: 1 - Planning
Classifier: Intended Audience :: Developers
Classifier: Programming Language :: Python :: 3
Classifier: Operating System :: Unix
Classifier: Operating System :: MacOS :: MacOS X
Classifier: Operating System :: Microsoft :: Windows
